era5tools/__init__.py
era5tools/era5tools.py
era5tools/clims/dummy.py
era5tools-0.0.4.dist-info/METADATA
era5tools-0.0.4.dist-info/WHEEL
era5tools-0.0.4.dist-info/licenses/LICENSE
era5tools-0.0.4.dist-info/RECORD
