Metadata-Version: 2.3
Name: era5tools
Version: 0.0.4
Summary: Tools for processing ECMWF ERA5 reanalysis
Project-URL: Homepage, https://github.com/MutaharChalmers/era5tools
Author-email: Mutahar Chalmers <mutahar.chalmers@gmail.com>
License: MIT License
License-File: LICENSE
Classifier: Development Status :: 4 - Beta
Classifier: Intended Audience :: Science/Research
Classifier: License :: OSI Approved :: MIT License
Classifier: Operating System :: OS Independent
Classifier: Programming Language :: Python :: 3
Classifier: Topic :: Scientific/Engineering
Requires-Python: >=3.8
Requires-Dist: cdsapi>=0.7.0
Requires-Dist: cfgrib>=0.9.14
Requires-Dist: climperiods>=0.0.2
Requires-Dist: eccodes>=1.7.1
Requires-Dist: numpy>=1.18
Requires-Dist: scipy>=1.10
Requires-Dist: xarray>=2023.01.0
Requires-Dist: zarr>=2.18
